mmpi/__init__.py
mmpi/main.py
mmpi/misc.py
mmpi/common/__init__.py
mmpi/common/abstracts.py
mmpi/common/clsid.py
mmpi/common/codepages.py
mmpi/common/exceptions.py
mmpi/common/filetypes.py
mmpi/common/lnk.py
mmpi/common/oleobj.py
mmpi/common/olevba.py
mmpi/common/rtfextract.py
mmpi/core/__init__.py
mmpi/core/plugins.py
mmpi/core/startup.py
mmpi/data/signatures/__init__.py
mmpi/data/signatures/compat.py
mmpi/data/signatures/eml/__init__.py
mmpi/data/signatures/eml/eml_infos.py
mmpi/data/signatures/html/__init__.py
mmpi/data/signatures/html/html_infos.py
mmpi/data/signatures/lnk/__init__.py
mmpi/data/signatures/lnk/lnk_infos.py
mmpi/data/signatures/ole/__init__.py
mmpi/data/signatures/ole/ole_infos.py
mmpi/data/signatures/other/__init__.py
mmpi/data/signatures/other/other_infos.py
mmpi/data/signatures/rtf/__init__.py
mmpi/data/signatures/rtf/rtf_infos.py
mmpi/data/signatures/zip/__init__.py
mmpi/data/signatures/zip/zip_infos.py
mmpi/data/white/__init__.py
mmpi/data/white/filter_domains.txt
mmpi/data/white/short_domains.txt
mmpi/data/yara/exe/exe.yara
mmpi/data/yara/pdf/pdf.yara
mmpi/data/yara/vba/vba.yara
mmpi/processing/__init__.py
mmpi/processing/emailparser.py
mmpi/processing/htmlparser.py
mmpi/processing/lnkparser.py
mmpi/processing/oleparser.py
mmpi/processing/otherparser.py
mmpi/processing/rtfparser.py
mmpi/processing/zipparser.py
mmpi-0.1.3.dist-info/LICENSE
mmpi-0.1.3.dist-info/METADATA
mmpi-0.1.3.dist-info/WHEEL
mmpi-0.1.3.dist-info/entry_points.txt
mmpi-0.1.3.dist-info/top_level.txt
mmpi-0.1.3.dist-info/RECORD
