Metadata-Version: 2.1
Name: mmpi
Version: 0.1.3
Summary: email detected library
Home-page: https://github.com/a232319779/mmpi
Author: ddvv
Author-email: dadavivi512@gmail.com
License: MIT
Platform: UNKNOWN
Classifier: Programming Language :: Python :: 3
Classifier: License :: OSI Approved :: MIT License
Classifier: Operating System :: OS Independent
Requires-Python: >=3.6
License-File: LICENSE
Requires-Dist: olefile (==0.46)
Requires-Dist: yara-python
